asyncio_workshop/__init__.py
asyncio_workshop/asyncio_workshop.py
asyncio_workshop-0.1.1.dist-info/AUTHORS.rst
asyncio_workshop-0.1.1.dist-info/LICENSE
asyncio_workshop-0.1.1.dist-info/METADATA
asyncio_workshop-0.1.1.dist-info/WHEEL
asyncio_workshop-0.1.1.dist-info/top_level.txt
asyncio_workshop-0.1.1.dist-info/RECORD
