Metadata-Version: 2.1
Name: asyncio-workshop
Version: 0.1.1
Summary: Create and combine asyncio workers easily.
Home-page: https://github.com/pocketguy/asyncio_workshop
Author: Nikita Kulakov
Author-email: kul7nik@gmail.com
License: MIT license
Keywords: asyncio_workshop
Platform: UNKNOWN
Classifier: Development Status :: 2 - Pre-Alpha
Classifier: Intended Audience :: Developers
Classifier: License :: OSI Approved :: MIT License
Classifier: Natural Language :: English
Classifier: Programming Language :: Python :: 2
Classifier: Programming Language :: Python :: 2.7
Classifier: Programming Language :: Python :: 3
Classifier: Programming Language :: Python :: 3.4
Classifier: Programming Language :: Python :: 3.5
Classifier: Programming Language :: Python :: 3.6
Classifier: Programming Language :: Python :: 3.7
